README
setup.py
ky/__init__.py
ky/api.py
kysdk.egg-info/PKG-INFO
kysdk.egg-info/SOURCES.txt
kysdk.egg-info/dependency_links.txt
kysdk.egg-info/top_level.txt