Metadata-Version: 1.1
Name: kysdk
Version: 0.2.6
Summary: see doc at http://doc.kuaiyutech.com
Home-page: http://packages.python.org/kysdk
Author: ShangHai Shilai
Author-email: developers@kuaiyutech.com
License: BSD
Keywords: stock kuaiyutech
Platform: UNKNOWN
Classifier: Development Status :: 3 - Alpha
Classifier: Environment :: Web Environment
Classifier: Intended Audience :: Developers
Classifier: License :: OSI Approved :: BSD License
Classifier: Operating System :: OS Independent
Classifier: Programming Language :: Python
